[{"id":1,"first_name":"An","last_name":"Phạm","email":"anpham0@edublogs.org","date_of_birth":"2015-05-05T06:18:12Z","age":56,"country":"Malaysia","phone":"8898927667"},
{"id":2,"first_name":"Hà","last_name":"Nguyễn","email":"hanguyen1@joomla.org","date_of_birth":"1982-05-01T03:16:30Z","age":26,"country":"Pakistan","phone":"2315313399"},
{"id":3,"first_name":"Minh","last_name":"Trần","email":"minhtran2@vkontakte.ru","date_of_birth":"1996-02-01T16:48:16Z","age":27,"country":"China","phone":"7287791978"},
{"id":4,"first_name":"Thảo","last_name":"Võ","email":"thaovo3@latimes.com","date_of_birth":"2008-10-16T02:38:43Z","age":33,"country":"Croatia","phone":"5203993323"},
{"id":5,"first_name":"Quỳnh","last_name":"Hoàng","email":"quynhhoang4@google.ru","date_of_birth":"1972-09-28T23:22:11Z","age":31,"country":"Macedonia","phone":"1026280679"},
{"id":6,"first_name":"Linh","last_name":"Trần","email":"linhtran5@instagram.com","date_of_birth":"1971-09-24T06:48:16Z","age":38,"country":"Portugal","phone":"3845060667"},
{"id":7,"first_name":"Hương","last_name":"Đặng","email":"huongdang6@telegraph.co.uk","date_of_birth":"1987-05-07T09:54:16Z","age":44,"country":"Mexico","phone":"9758708783"},
{"id":8,"first_name":"Diệp","last_name":"Lê","email":"dieple7@rakuten.co.jp","date_of_birth":"1984-10-07T23:12:44Z","age":56,"country":"Malaysia","phone":"6573041812"},
{"id":9,"first_name":"Hằng","last_name":"Nguyễn","email":"hangnguyen8@soundcloud.com","date_of_birth":"1985-03-09T18:33:58Z","age":39,"country":"Panama","phone":"7644875762"},
{"id":10,"first_name":"Trúc","last_name":"Trần","email":"tructran9@washingtonpost.com","date_of_birth":"1999-03-02T04:59:39Z","age":58,"country":"Panama","phone":"7268934858"},
{"id":11,"first_name":"Bích","last_name":"Địch","email":"bichdicha@comcast.net","date_of_birth":"2022-02-16T11:45:51Z","age":43,"country":"Saudi Arabia","phone":"2648248025"},
{"id":12,"first_name":"Vân","last_name":"Nguyễn","email":"vannguyenb@cpanel.net","date_of_birth":"1978-06-17T13:18:36Z","age":52,"country":"Honduras","phone":"8266326863"},
{"id":13,"first_name":"Thảo","last_name":"Lý","email":"thaoly@ow.ly","date_of_birth":"1990-01-13T23:15:49Z","age":56,"country":"Mongolia","phone":"9266496918"},
{"id":14,"first_name":"Huy","last_name":"Trần","email":"huytran@google.com","date_of_birth":"2008-09-05T15:06:44Z","age":24,"country":"Brazil","phone":"8356718733"},
{"id":15,"first_name":"Đức","last_name":"Lê","email":"ducle@imdb.com","date_of_birth":"1979-01-21T17:30:14Z","age":37,"country":"Brazil","phone":"2793619358"},
{"id":16,"first_name":"Thành","last_name":"Võ","email":"thanhvo@redcross.org","date_of_birth":"2013-04-11T06:28:17Z","age":30,"country":"Portugal","phone":"7025842713"},
{"id":17,"first_name":"Hải","last_name":"Nguyễn","email":"hainguyen@t-online.de","date_of_birth":"1971-07-25T09:11:42Z","age":25,"country":"Brazil","phone":"6935088381"},
{"id":18,"first_name":"Thảo","last_name":"Trần","email":"thaotran@ustream.tv","date_of_birth":"1993-11-19T20:00:14Z","age":36,"country":"China","phone":"5879989795"},
{"id":19,"first_name":"Thành","last_name":"Đào","email":"thanhdao@mozilla.com","date_of_birth":"2003-08-19T21:35:13Z","age":40,"country":"Burkina Faso","phone":"9082374422"},
{"id":20,"first_name":"Thảo","last_name":"Nguyễn","email":"thaonguyen@wired.com","date_of_birth":"1974-08-19T08:58:18Z","age":23,"country":"Philippines","phone":"6089603213"},
{"id":21,"first_name":"Chloette","last_name":"Huygens","email":"chuygensk@blinklist.com","date_of_birth":"2005-04-14T07:32:02Z","age":49,"country":"China","phone":"3223205651"},
{"id":22,"first_name":"Daryl","last_name":"Edelman","email":"dedelmanl@cpanel.net","date_of_birth":"2022-02-06T13:57:43Z","age":32,"country":"China","phone":"5977148675"},
{"id":23,"first_name":"Philip","last_name":"Clacey","email":"pclaceym@arizona.edu","date_of_birth":"1979-02-27T02:24:00Z","age":54,"country":"Indonesia","phone":"4262741122"},
{"id":24,"first_name":"Emmalee","last_name":"Olesen","email":"eolesenn@github.io","date_of_birth":"2016-08-06T19:50:52Z","age":28,"country":"Bosnia and Herzegovina","phone":"9589530808"},
{"id":25,"first_name":"Kellen","last_name":"Matelaitis","email":"kmatelaitiso@jigsy.com","date_of_birth":"2014-10-16T05:52:59Z","age":35,"country":"Indonesia","phone":"9682678408"},
{"id":26,"first_name":"Erny","last_name":"Windybank","email":"ewindybankp@ovh.net","date_of_birth":"2000-10-16T07:03:05Z","age":54,"country":"Poland","phone":"7005234410"},
{"id":27,"first_name":"Ellissa","last_name":"Ranvoise","email":"eranvoiseq@harvard.edu","date_of_birth":"1993-07-20T17:41:32Z","age":46,"country":"Indonesia","phone":"3147595755"},
{"id":28,"first_name":"Thatcher","last_name":"Alves","email":"talvesr@loc.gov","date_of_birth":"2012-12-18T05:20:06Z","age":44,"country":"Russia","phone":"3406162850"},
{"id":29,"first_name":"Lucian","last_name":"Archibould","email":"larchiboulds@spiegel.de","date_of_birth":"1987-10-12T03:44:57Z","age":38,"country":"Israel","phone":"1926589327"},
{"id":30,"first_name":"Ileana","last_name":"Mease","email":"imeaset@newsvine.com","date_of_birth":"1999-09-19T10:44:32Z","age":21,"country":"Indonesia","phone":"3378350994"},
{"id":31,"first_name":"Joey","last_name":"Sebring","email":"jsebringu@alexa.com","date_of_birth":"2018-04-19T00:35:23Z","age":57,"country":"China","phone":"9826371138"},
{"id":32,"first_name":"Deb","last_name":"Renouf","email":"drenoufv@pen.io","date_of_birth":"1985-03-05T08:10:29Z","age":22,"country":"Philippines","phone":"1879122241"},
{"id":33,"first_name":"Guenevere","last_name":"Perle","email":"gperlew@geocities.jp","date_of_birth":"1973-03-02T05:08:55Z","age":55,"country":"Argentina","phone":"5587401616"},
{"id":34,"first_name":"Derrek","last_name":"Luckman","email":"dluckmanx@technorati.com","date_of_birth":"2009-01-23T08:56:29Z","age":19,"country":"Philippines","phone":"3705065316"},
{"id":35,"first_name":"Rockwell","last_name":"Getley","email":"rgetleyy@imgur.com","date_of_birth":"1987-04-03T02:50:27Z","age":21,"country":"Brazil","phone":"9307841819"},
{"id":36,"first_name":"Nadiya","last_name":"Colliver","email":"ncolliverz@e-recht24.de","date_of_birth":"1970-10-31T23:12:06Z","age":23,"country":"Ethiopia","phone":"9823969322"},
{"id":37,"first_name":"Christian","last_name":"Bento","email":"cbento10@telegraph.co.uk","date_of_birth":"1989-01-03T16:26:25Z","age":50,"country":"Lithuania","phone":"4179018520"},
{"id":38,"first_name":"Junette","last_name":"Massey","email":"jmassey11@pbs.org","date_of_birth":"1994-04-26T21:21:09Z","age":53,"country":"Philippines","phone":"7474205936"},
{"id":39,"first_name":"Gabbi","last_name":"Freiberg","email":"gfreiberg12@t.co","date_of_birth":"1981-06-27T02:27:51Z","age":46,"country":"China","phone":"5076079678"},
{"id":40,"first_name":"Blayne","last_name":"Redmile","email":"bredmile13@virginia.edu","date_of_birth":"2010-10-31T22:43:24Z","age":40,"country":"China","phone":"7713236928"},
{"id":41,"first_name":"Eryn","last_name":"Ashlin","email":"eashlin14@qq.com","date_of_birth":"2010-08-01T21:06:59Z","age":36,"country":"China","phone":"1223189786"},
{"id":42,"first_name":"Gwyneth","last_name":"Hawkett","email":"ghawkett15@un.org","date_of_birth":"1988-01-20T22:26:29Z","age":46,"country":"Sweden","phone":"1963993907"},
{"id":43,"first_name":"Ellsworth","last_name":"Gosling","email":"egosling16@hubpages.com","date_of_birth":"1988-09-02T01:24:59Z","age":37,"country":"China","phone":"9365690834"},
{"id":44,"first_name":"Pauli","last_name":"Sansome","email":"psansome17@salon.com","date_of_birth":"2011-06-11T05:58:34Z","age":42,"country":"Indonesia","phone":"7147203572"},
{"id":45,"first_name":"Geraldine","last_name":"Bunting","email":"gbunting18@apache.org","date_of_birth":"2002-12-20T13:44:34Z","age":43,"country":"China","phone":"3666124608"},
{"id":46,"first_name":"Shandy","last_name":"Borrott","email":"sborrott19@dion.ne.jp","date_of_birth":"1997-09-07T17:03:29Z","age":23,"country":"Indonesia","phone":"1752047042"},
{"id":47,"first_name":"Jayson","last_name":"Eckhard","email":"jeckhard1a@meetup.com","date_of_birth":"1974-03-22T00:26:17Z","age":51,"country":"Indonesia","phone":"3338922479"},
{"id":48,"first_name":"Nell","last_name":"Ashbey","email":"nashbey1b@so-net.ne.jp","date_of_birth":"1988-11-20T19:50:45Z","age":37,"country":"Sweden","phone":"5411136873"},
{"id":49,"first_name":"Care","last_name":"Portinari","email":"cportinari1c@gmpg.org","date_of_birth":"1976-01-25T21:16:30Z","age":33,"country":"China","phone":"5214653000"},
{"id":50,"first_name":"Peggi","last_name":"Brisker","email":"pbrisker1d@jalbum.net","date_of_birth":"1973-03-25T17:32:03Z","age":42,"country":"China","phone":"5465625136"}]